favico/__init__.py
favico/cli.py
favico/favico.py
favico-0.1.8.dist-info/AUTHORS.rst
favico-0.1.8.dist-info/LICENSE
favico-0.1.8.dist-info/METADATA
favico-0.1.8.dist-info/WHEEL
favico-0.1.8.dist-info/entry_points.txt
favico-0.1.8.dist-info/top_level.txt
favico-0.1.8.dist-info/RECORD
